README.md
setup.py
flexible_thread_pool/__init__.py
flexible_thread_pool.egg-info/PKG-INFO
flexible_thread_pool.egg-info/SOURCES.txt
flexible_thread_pool.egg-info/dependency_links.txt
flexible_thread_pool.egg-info/requires.txt
flexible_thread_pool.egg-info/top_level.txt