Metadata-Version: 2.1
Name: flexible-thread-pool
Version: 0.2
Summary: flexible_thread_pool ，auto expand thread and reduce threads. both support sync and asyncio,fast than concurrent.futures.ThreadpoolExecutor
Home-page: https://github.com/ydf0509/flexible_thread_pool
Author: bfzs
Author-email: ydf0509@sohu.com
Maintainer: ydf
Maintainer-email: ydf0509@sohu.com
License: BSD License
Keywords: thread pool,async,asyncio,auto scala,flexible_thread_pool
Platform: all
Classifier: Development Status :: 4 - Beta
Classifier: Operating System :: OS Independent
Classifier: Intended Audience :: Developers
Classifier: License :: OSI Approved :: BSD License
Classifier: Programming Language :: Python
Classifier: Programming Language :: Python :: Implementation
Classifier: Programming Language :: Python :: 3.6
Classifier: Programming Language :: Python :: 3.7
Classifier: Programming Language :: Python :: 3.8
Classifier: Programming Language :: Python :: 3.9
Classifier: Programming Language :: Python :: 3.10
Classifier: Programming Language :: Python :: 3.11
Classifier: Topic :: Software Development :: Libraries
